{
  "space": {
    "inset": {
      "balanced": {
        "s": {
          "value": "{bb.size.fluid.50}",
          "type": "spacing"
        },
        "m": {
          "value": "{bb.size.fluid.75}",
          "type": "spacing"
        },
        "l": {
          "value": "{bb.size.fluid.125}",
          "type": "spacing"
        },
        "xl": {
          "value": "{bb.size.fluid.200}",
          "type": "spacing"
        }
      }
    }
  },
  "type": {
    "body": {
      "m": {
        "value": {
          "fontSize": "{bb.font.size.100}",
          "fontFamily": "{bb.font.family.sans}",
          "fontWeight": "{bb.font.style.regular}",
          "lineHeight": "{bb.line-height.100}"
        },
        "type": "typography"
      }
    }
  },
  "size": {
    "icon": {
      "xl": {
        "value": "{bb.size.fluid.200}",
        "type": "sizing"
      }
    }
  }
}