{
  "type": {
    "body": {
      "m": {
        "$type": "typography",
        "$value": {
          "fontSize": "{font.size.body.m}",
          "lineHeight": "{font.line_height.body.m}",
          "fontFamily": "{font.family.sans}",
          "fontWeight": "{font.style.body.m}"
        }
      }
    }
  },
  "font": {
    "size": {
      "body": {
        "m": {
          "$type": "fontSizes",
          "$value": "{sky.text.size.200}"
        }
      }
    },
    "line_height": {
      "body": {
        "m": {
          "$type": "lineHeights",
          "$value": "{sky.text.line-height.200}"
        }
      }
    },
    "style": {
      "body": {
        "m": {
          "$type": "fontWeights",
          "$value": "{sky.style.regular}"
        }
      }
    },
    "family": {
      "sans": {
        "$type": "fontFamilies",
        "$value": "{bb.font.family.sans}"
      }
    }
  },
  "space": {
    "inset": {
      "balanced": {
        "m": {
          "$type": "spacing",
          "$value": "{sky.size.9}"
        },
        "s": {
          "$type": "spacing",
          "$value": "{sky.size.8}"
        }
      }
    },
    "icon_gap": {
      "m": {
        "$type": "spacing",
        "$value": "{sky.size.15}"
      }
    },
    "text_action": {
      "gap": {
        "$type": "spacing",
        "$value": "{sky.size.15}"
      }
    }
  },
  "icon": {
    "size": {
      "xl": {
        "$type": "sizing",
        "$value": "{sky.size.32}"
      },
      "m": {
        "$type": "sizing",
        "$value": "{sky.size.16}"
      }
    }
  },
  "text": {
    "font_family": {
      "$type": "text",
      "$value": "{sky.font.name}"
    }
  }
}