{
  "color": {
    "text": {
      "default": {
        "$type": "color",
        "$value": "{bb.color.gray.900}"
      },
      "deemphasized": {
        "$type": "color",
        "$value": "{bb.color.gray.600}"
      },
      "action": {
        "$type": "color",
        "$value": "{bb.color.blue.600}"
      },
      "danger": {
        "$type": "color",
        "$value": "{bb.color.red.600}"
      },
      "inverse": {
        "$type": "color",
        "$value": "{bb.color.white}"
      },
      "selected": {
        "$type": "color",
        "$value": "{bb.color.blue.600}"
      },
      "heading": {
        "$type": "color",
        "$value": "{bb.color.gray.1100}"
      },
      "action_contrast": {
        "$type": "color",
        "$value": "{bb.color.blue.700}"
      }
    },
    "icon": {
      "default": {
        "$type": "color",
        "$value": "{bb.color.gray.900}"
      },
      "deemphasized": {
        "$type": "color",
        "$value": "{bb.color.gray.600}"
      },
      "action": {
        "$type": "color",
        "$value": "{bb.color.blue.600}"
      },
      "danger": {
        "$type": "color",
        "$value": "{bb.color.red.600}"
      },
      "warning": {
        "$type": "color",
        "$value": "{bb.color.yellow.400}"
      },
      "success": {
        "$type": "color",
        "$value": "{bb.color.green.600}"
      },
      "info": {
        "$type": "color",
        "$value": "{bb.color.blue.600}"
      },
      "inverse": {
        "$type": "color",
        "$value": "{bb.color.white}"
      },
      "selected": {
        "$type": "color",
        "$value": "{bb.color.blue.600}"
      },
      "eyebrow": {
        "$type": "color",
        "$value": "{bb.color.brand.impact_green}"
      },
      "input": {
        "action": {
          "$type": "color",
          "$value": "{bb.color.gray.600}"
        }
      }
    },
    "background": {
      "page": {
        "$type": "color",
        "$value": "{bb.color.gray.100}"
      },
      "scrim": {
        "$type": "color",
        "$value": "{bb.color.scrim}"
      },
      "disabled": {
        "$type": "color",
        "$value": "{bb.color.gray.100}"
      },
      "blocking": {
        "$type": "color",
        "$value": "{bb.color.rgba.white.70}"
      },
      "text_highlight": {
        "$type": "color",
        "$value": "{bb.color.yellow.300}"
      },
      "file_drop": {
        "$type": "color",
        "$value": "{bb.color.gray.25}"
      },
      "thumbnail_matte": {
        "$type": "color",
        "$value": "{bb.color.white}"
      },
      "action": {
        "primary": {
          "base": {
            "$type": "color",
            "$value": "{bb.color.blue.600}"
          },
          "hover": {
            "$type": "color",
            "$value": "{bb.color.blue.700}"
          },
          "active": {
            "$type": "color",
            "$value": "{bb.color.blue.800}"
          },
          "focus": {
            "$type": "color",
            "$value": "{bb.color.blue.600}"
          },
          "disabled": {
            "$type": "color",
            "$value": "{color.background.disabled}"
          }
        },
        "secondary": {
          "base": {
            "$type": "color",
            "$value": "{bb.color.white}"
          },
          "hover": {
            "$type": "color",
            "$value": "{bb.color.blue.50}"
          },
          "active": {
            "$type": "color",
            "$value": "{bb.color.blue.100}"
          },
          "focus": {
            "$type": "color",
            "$value": "{bb.color.white}"
          },
          "disabled": {
            "$type": "color",
            "$value": "{color.background.disabled}"
          }
        },
        "tertiary": {
          "base": {
            "$type": "color",
            "$value": "{bb.color.transparent}"
          },
          "hover": {
            "$type": "color",
            "$value": "{bb.color.blue.50}"
          },
          "active": {
            "$type": "color",
            "$value": "{bb.color.blue.100}"
          },
          "focus": {
            "$type": "color",
            "$value": "{bb.color.transparent}"
          },
          "disabled": {
            "$type": "color",
            "$value": "{color.background.disabled}"
          }
        },
        "danger": {
          "base": {
            "$type": "color",
            "$value": "{bb.color.red.600}"
          },
          "hover": {
            "$type": "color",
            "$value": "{bb.color.red.700}"
          },
          "active": {
            "$type": "color",
            "$value": "{bb.color.red.800}"
          },
          "focus": {
            "$type": "color",
            "$value": "{bb.color.red.600}"
          },
          "disabled": {
            "$type": "color",
            "$value": "{color.background.disabled}"
          }
        },
        "input": {
          "base": {
            "$type": "color",
            "$value": "{bb.color.white}"
          },
          "hover": {
            "$type": "color",
            "$value": "{bb.color.blue.50}"
          },
          "active": {
            "$type": "color",
            "$value": "{bb.color.blue.100}"
          },
          "focus": {
            "$type": "color",
            "$value": "{bb.color.white}"
          },
          "disabled": {
            "$type": "color",
            "$value": "{color.background.disabled}"
          }
        },
        "accent": {
          "base": {
            "$type": "color",
            "$value": "{bb.color.white}"
          },
          "hover": {
            "$type": "color",
            "$value": "{bb.color.blue.50}"
          },
          "active": {
            "$type": "color",
            "$value": "{bb.color.blue.100}"
          },
          "focus": {
            "$type": "color",
            "$value": "{bb.color.white}"
          },
          "disabled": {
            "$type": "color",
            "$value": "{color.background.disabled}"
          }
        }
      },
      "container": {
        "base": {
          "$type": "color",
          "$value": "{bb.color.white}"
        },
        "menu": {
          "$type": "color",
          "$value": "{bb.color.white}"
        },
        "danger": {
          "$type": "color",
          "$value": "{bb.color.red.200}"
        },
        "warning": {
          "$type": "color",
          "$value": "{bb.color.yellow.200}"
        },
        "success": {
          "$type": "color",
          "$value": "{bb.color.green.200}"
        },
        "info": {
          "$type": "color",
          "$value": "{bb.color.blue.200}"
        },
        "dimmed": {
          "$type": "color",
          "$value": "{bb.color.gray.25}"
        },
        "tooltip": {
          "$type": "color",
          "$value": "{bb.color.gray.900}"
        }
      },
      "icon_matte": {
        "danger": {
          "$type": "color",
          "$value": "{bb.color.red.600}"
        },
        "warning": {
          "$type": "color",
          "$value": "{bb.color.yellow.400}"
        },
        "success": {
          "$type": "color",
          "$value": "{bb.color.green.600}"
        },
        "info": {
          "$type": "color",
          "$value": "{bb.color.blue.600}"
        },
        "action": {
          "heavy": {
            "$type": "color",
            "$value": "{bb.color.blue.600}"
          },
          "soft": {
            "$type": "color",
            "$value": "{bb.color.blue.100}"
          }
        }
      },
      "input": {
        "base": {
          "$type": "color",
          "$value": "{bb.color.white}"
        },
        "disabled": {
          "$type": "color",
          "$value": "{color.background.disabled}"
        }
      },
      "row": {
        "base": {
          "$type": "color",
          "$value": "{bb.color.white}"
        },
        "hover": {
          "$type": "color",
          "$value": "{bb.color.blue.50}"
        },
        "active": {
          "$type": "color",
          "$value": "{bb.color.blue.100}"
        },
        "focus": {
          "$type": "color",
          "$value": "{bb.color.white}"
        },
        "disabled": {
          "$type": "color",
          "$value": "{color.background.disabled}"
        }
      },
      "nav": {
        "base": {
          "$type": "color",
          "$value": "{bb.color.transparent}"
        },
        "hover": {
          "$type": "color",
          "$value": "{bb.color.blue.50}"
        },
        "active": {
          "$type": "color",
          "$value": "{bb.color.blue.100}"
        },
        "focus": {
          "$type": "color",
          "$value": "{bb.color.transparent}"
        },
        "disabled": {
          "$type": "color",
          "$value": "{color.background.disabled}"
        }
      },
      "selected": {
        "heavy": {
          "$type": "color",
          "$value": "{bb.color.blue.600}"
        },
        "soft": {
          "$type": "color",
          "$value": "{bb.color.blue.100}"
        },
        "danger": {
          "$type": "color",
          "$value": "{bb.color.red.200}"
        },
        "warning": {
          "$type": "color",
          "$value": "{bb.color.yellow.200}"
        },
        "success": {
          "$type": "color",
          "$value": "{bb.color.green.200}"
        },
        "switch": {
          "base": {
            "$type": "color",
            "$value": "{bb.color.blue.600}"
          },
          "disabled": {
            "$type": "color",
            "$value": "{color.background.disabled}"
          }
        }
      },
      "thumb": {
        "base": {
          "$type": "color",
          "$value": "{bb.color.white}"
        },
        "disabled": {
          "$type": "color",
          "$value": "{bb.color.gray.25}"
        }
      },
      "tab": {
        "base": {
          "$type": "color",
          "$value": "{bb.color.transparent}"
        },
        "hover": {
          "$type": "color",
          "$value": "{bb.color.transparent}"
        },
        "active": {
          "$type": "color",
          "$value": "{bb.color.transparent}"
        },
        "focus": {
          "$type": "color",
          "$value": "{bb.color.transparent}"
        },
        "selected": {
          "$type": "color",
          "$value": "{bb.color.transparent}"
        },
        "disabled": {
          "$type": "color",
          "$value": "{color.background.disabled}"
        },
        "wizard": {
          "disabled": {
            "$type": "color",
            "$value": "{bb.color.transparent}"
          }
        }
      }
    },
    "border": {
      "selected": {
        "$type": "color",
        "$value": "{bb.color.blue.600}"
      },
      "selected_soft": {
        "$type": "color",
        "$value": "{bb.color.blue.300}"
      },
      "danger": {
        "$type": "color",
        "$value": "{bb.color.red.600}"
      },
      "warning": {
        "$type": "color",
        "$value": "{bb.color.yellow.400}"
      },
      "success": {
        "$type": "color",
        "$value": "{bb.color.green.600}"
      },
      "info": {
        "$type": "color",
        "$value": "{bb.color.blue.600}"
      },
      "divider": {
        "$type": "color",
        "$value": "{bb.color.gray.300}"
      },
      "elevation": {
        "$type": "color",
        "$value": "{bb.color.gray.200}"
      },
      "disabled": {
        "$type": "color",
        "$value": "{bb.color.gray.300}"
      },
      "column_divider": {
        "$type": "color",
        "$value": "{bb.color.blue.600}"
      },
      "text_highlight": {
        "$type": "color",
        "$value": "{bb.color.yellow.700}"
      },
      "progress_step": {
        "$type": "color",
        "$value": "{bb.color.gray.400}"
      },
      "action": {
        "primary": {
          "base": {
            "$type": "color",
            "$value": "{bb.color.blue.600}"
          },
          "hover": {
            "$type": "color",
            "$value": "{bb.color.blue.1000}"
          },
          "active": {
            "$type": "color",
            "$value": "{bb.color.blue.1000}"
          },
          "focus": {
            "$type": "color",
            "$value": "{bb.color.blue.1000}"
          },
          "disabled": {
            "$type": "color",
            "$value": "{color.border.disabled}"
          }
        },
        "secondary": {
          "base": {
            "$type": "color",
            "$value": "{bb.color.gray.300}"
          },
          "hover": {
            "$type": "color",
            "$value": "{bb.color.blue.600}"
          },
          "active": {
            "$type": "color",
            "$value": "{bb.color.blue.600}"
          },
          "focus": {
            "$type": "color",
            "$value": "{bb.color.blue.600}"
          },
          "disabled": {
            "$type": "color",
            "$value": "{color.border.disabled}"
          }
        },
        "tertiary": {
          "base": {
            "$type": "color",
            "$value": "{bb.color.transparent}"
          },
          "hover": {
            "$type": "color",
            "$value": "{bb.color.blue.600}"
          },
          "active": {
            "$type": "color",
            "$value": "{bb.color.blue.600}"
          },
          "focus": {
            "$type": "color",
            "$value": "{bb.color.blue.600}"
          },
          "disabled": {
            "$type": "color",
            "$value": "{color.border.disabled}"
          }
        },
        "danger": {
          "base": {
            "$type": "color",
            "$value": "{bb.color.red.600}"
          },
          "hover": {
            "$type": "color",
            "$value": "{bb.color.red.1000}"
          },
          "active": {
            "$type": "color",
            "$value": "{bb.color.red.1000}"
          },
          "focus": {
            "$type": "color",
            "$value": "{bb.color.red.1000}"
          },
          "disabled": {
            "$type": "color",
            "$value": "{color.border.disabled}"
          }
        },
        "input": {
          "base": {
            "$type": "color",
            "$value": "{bb.color.gray.300}"
          },
          "hover": {
            "$type": "color",
            "$value": "{bb.color.blue.600}"
          },
          "active": {
            "$type": "color",
            "$value": "{bb.color.blue.600}"
          },
          "focus": {
            "$type": "color",
            "$value": "{bb.color.blue.600}"
          },
          "disabled": {
            "$type": "color",
            "$value": "{color.border.disabled}"
          }
        },
        "accent": {
          "base": {
            "$type": "color",
            "$value": "{bb.color.gray.200}"
          },
          "hover": {
            "$type": "color",
            "$value": "{bb.color.blue.600}"
          },
          "active": {
            "$type": "color",
            "$value": "{bb.color.blue.600}"
          },
          "focus": {
            "$type": "color",
            "$value": "{bb.color.blue.600}"
          },
          "disabled": {
            "$type": "color",
            "$value": "{color.border.disabled}"
          }
        }
      },
      "container": {
        "base": {
          "$type": "color",
          "$value": "{bb.color.gray.200}"
        }
      },
      "input": {
        "base": {
          "$type": "color",
          "$value": "{bb.color.gray.300}"
        },
        "hover": {
          "$type": "color",
          "$value": "{bb.color.blue.600}"
        },
        "active": {
          "$type": "color",
          "$value": "{bb.color.blue.600}"
        },
        "focus": {
          "$type": "color",
          "$value": "{bb.color.blue.600}"
        },
        "disabled": {
          "$type": "color",
          "$value": "{color.border.disabled}"
        },
        "error": {
          "$type": "color",
          "$value": "{bb.color.red.600}"
        }
      },
      "switch": {
        "base": {
          "$type": "color",
          "$value": "{bb.color.gray.500}"
        },
        "hover": {
          "$type": "color",
          "$value": "{bb.color.blue.600}"
        },
        "active": {
          "$type": "color",
          "$value": "{bb.color.blue.600}"
        },
        "focus": {
          "$type": "color",
          "$value": "{bb.color.blue.600}"
        },
        "disabled": {
          "$type": "color",
          "$value": "{color.border.disabled}"
        },
        "error": {
          "$type": "color",
          "$value": "{bb.color.red.600}"
        },
        "selected": {
          "base": {
            "$type": "color",
            "$value": "{bb.color.transparent}"
          },
          "hover": {
            "$type": "color",
            "$value": "{bb.color.blue.1000}"
          },
          "active": {
            "$type": "color",
            "$value": "{bb.color.blue.1000}"
          },
          "focus": {
            "$type": "color",
            "$value": "{bb.color.blue.1000}"
          },
          "disabled": {
            "$type": "color",
            "$value": "{color.border.disabled}"
          }
        }
      },
      "separator": {
        "light": {
          "$type": "color",
          "$value": "{bb.color.gray.200}"
        },
        "row": {
          "$type": "color",
          "$value": "{bb.color.gray.200}"
        }
      },
      "tab": {
        "base": {
          "$type": "color",
          "$value": "{bb.color.transparent}"
        },
        "hover": {
          "$type": "color",
          "$value": "{bb.color.blue.600}"
        },
        "active": {
          "$type": "color",
          "$value": "{bb.color.blue.600}"
        },
        "focus": {
          "$type": "color",
          "$value": "{bb.color.blue.600}"
        },
        "disabled": {
          "$type": "color",
          "$value": "{color.border.disabled}"
        },
        "wizard": {
          "disabled": {
            "$type": "color",
            "$value": "{bb.color.transparent}"
          }
        }
      },
      "nav": {
        "base": {
          "$type": "color",
          "$value": "{bb.color.transparent}"
        },
        "hover": {
          "$type": "color",
          "$value": "{bb.color.blue.600}"
        },
        "active": {
          "$type": "color",
          "$value": "{bb.color.blue.600}"
        },
        "focus": {
          "$type": "color",
          "$value": "{bb.color.blue.600}"
        },
        "disabled": {
          "$type": "color",
          "$value": "{color.border.disabled}"
        }
      }
    },
    "category": {
      "green": {
        "$type": "color",
        "$value": "{bb.color.green.200}"
      },
      "teal": {
        "$type": "color",
        "$value": "{bb.color.teal.200}"
      },
      "purple": {
        "$type": "color",
        "$value": "{bb.color.purple.200}"
      },
      "orange": {
        "$type": "color",
        "$value": "{bb.color.orange.200}"
      },
      "blue": {
        "$type": "color",
        "$value": "{bb.color.sky.200}"
      },
      "yellow": {
        "$type": "color",
        "$value": "{bb.color.yellow.200}"
      },
      "red": {
        "$type": "color",
        "$value": "{bb.color.red.200}"
      }
    },
    "illustration": {
      "stroke": {
        "$type": "color",
        "$value": "{bb.color.brand.trusted_blue}"
      },
      "fill": {
        "heavy": {
          "$type": "color",
          "$value": "{bb.color.green.300}"
        },
        "soft": {
          "$type": "color",
          "$value": "{bb.color.green.50}"
        },
        "softest": {
          "$type": "color",
          "$value": "{bb.color.white}"
        }
      }
    },
    "viz": {
      "axis": {
        "$type": "color",
        "$value": "{bb.color.gray.500}"
      },
      "gridline": {
        "$type": "color",
        "$value": "{bb.color.gray.200}"
      },
      "marker": {
        "$type": "color",
        "$value": "{bb.color.gray.900}"
      },
      "category": {
        "1": {
          "$type": "color",
          "$value": "{bb.color.teal.500}"
        },
        "2": {
          "$type": "color",
          "$value": "{bb.color.purple.800}"
        },
        "3": {
          "$type": "color",
          "$value": "{bb.color.blue.500}"
        },
        "4": {
          "$type": "color",
          "$value": "{bb.color.sky.900}"
        },
        "5": {
          "$type": "color",
          "$value": "{bb.color.orange.600}"
        },
        "6": {
          "$type": "color",
          "$value": "{bb.color.red.800}"
        },
        "7": {
          "$type": "color",
          "$value": "{bb.color.pink.600}"
        },
        "8": {
          "$type": "color",
          "$value": "{bb.color.green.700}"
        }
      },
      "sequence": {
        "1": {
          "$type": "color",
          "$value": "{bb.color.teal.100}"
        },
        "2": {
          "$type": "color",
          "$value": "{bb.color.teal.200}"
        },
        "3": {
          "$type": "color",
          "$value": "{bb.color.teal.300}"
        },
        "4": {
          "$type": "color",
          "$value": "{bb.color.teal.400}"
        },
        "5": {
          "$type": "color",
          "$value": "{bb.color.teal.500}"
        },
        "6": {
          "$type": "color",
          "$value": "{bb.color.teal.600}"
        },
        "7": {
          "$type": "color",
          "$value": "{bb.color.teal.700}"
        },
        "8": {
          "$type": "color",
          "$value": "{bb.color.teal.800}"
        },
        "9": {
          "$type": "color",
          "$value": "{bb.color.teal.900}"
        },
        "10": {
          "$type": "color",
          "$value": "{bb.color.teal.1000}"
        }
      },
      "diverge": {
        "neg": {
          "1": {
            "$type": "color",
            "$value": "{bb.color.red.100}"
          },
          "2": {
            "$type": "color",
            "$value": "{bb.color.red.200}"
          },
          "3": {
            "$type": "color",
            "$value": "{bb.color.red.300}"
          },
          "4": {
            "$type": "color",
            "$value": "{bb.color.red.400}"
          },
          "5": {
            "$type": "color",
            "$value": "{bb.color.red.500}"
          },
          "6": {
            "$type": "color",
            "$value": "{bb.color.red.600}"
          },
          "7": {
            "$type": "color",
            "$value": "{bb.color.red.700}"
          },
          "8": {
            "$type": "color",
            "$value": "{bb.color.red.800}"
          },
          "9": {
            "$type": "color",
            "$value": "{bb.color.red.900}"
          },
          "10": {
            "$type": "color",
            "$value": "{bb.color.red.1000}"
          }
        },
        "pos": {
          "1": {
            "$type": "color",
            "$value": "{bb.color.blue.100}"
          },
          "2": {
            "$type": "color",
            "$value": "{bb.color.blue.200}"
          },
          "3": {
            "$type": "color",
            "$value": "{bb.color.blue.300}"
          },
          "4": {
            "$type": "color",
            "$value": "{bb.color.blue.400}"
          },
          "5": {
            "$type": "color",
            "$value": "{bb.color.blue.500}"
          },
          "6": {
            "$type": "color",
            "$value": "{bb.color.blue.600}"
          },
          "7": {
            "$type": "color",
            "$value": "{bb.color.blue.700}"
          },
          "8": {
            "$type": "color",
            "$value": "{bb.color.blue.800}"
          },
          "9": {
            "$type": "color",
            "$value": "{bb.color.blue.900}"
          },
          "10": {
            "$type": "color",
            "$value": "{bb.color.blue.1000}"
          }
        }
      }
    },
    "classify": {
      "1": {
        "heavy": {
          "$type": "color",
          "$value": "{bb.color.teal.700}"
        },
        "soft": {
          "$type": "color",
          "$value": "{bb.color.teal.200}"
        }
      },
      "2": {
        "heavy": {
          "$type": "color",
          "$value": "{bb.color.purple.700}"
        },
        "soft": {
          "$type": "color",
          "$value": "{bb.color.purple.200}"
        }
      },
      "3": {
        "heavy": {
          "$type": "color",
          "$value": "{bb.color.sky.700}"
        },
        "soft": {
          "$type": "color",
          "$value": "{bb.color.sky.200}"
        }
      },
      "4": {
        "heavy": {
          "$type": "color",
          "$value": "{bb.color.orange.700}"
        },
        "soft": {
          "$type": "color",
          "$value": "{bb.color.orange.200}"
        }
      },
      "5": {
        "heavy": {
          "$type": "color",
          "$value": "{bb.color.pink.700}"
        },
        "soft": {
          "$type": "color",
          "$value": "{bb.color.pink.200}"
        }
      },
      "6": {
        "heavy": {
          "$type": "color",
          "$value": "{bb.color.green.700}"
        },
        "soft": {
          "$type": "color",
          "$value": "{bb.color.green.200}"
        }
      },
      "7": {
        "heavy": {
          "$type": "color",
          "$value": "{bb.color.red.700}"
        },
        "soft": {
          "$type": "color",
          "$value": "{bb.color.red.200}"
        }
      }
    }
  },
  "elevation": {
    "none": {
      "$type": "boxShadow",
      "$value": "{bb.shadow.gray.0}"
    },
    "focus": {
      "$type": "boxShadow",
      "$value": "{bb.shadow.gray.200}"
    },
    "overflow": {
      "$type": "boxShadow",
      "$value": "{bb.shadow.gray.200}"
    },
    "raised": {
      "100": {
        "$type": "boxShadow",
        "$value": "{bb.shadow.gray.100}"
      }
    },
    "overlay": {
      "100": {
        "$type": "boxShadow",
        "$value": "{bb.shadow.gray.400}"
      },
      "200": {
        "$type": "boxShadow",
        "$value": "{bb.shadow.gray.800}"
      },
      "300": {
        "$type": "boxShadow",
        "$value": "{bb.shadow.gray.1600}"
      },
      "400": {
        "$type": "boxShadow",
        "$value": "{bb.shadow.gray.2400}"
      }
    },
    "action": {
      "primary": {
        "base": {
          "$type": "boxShadow",
          "$value": "{bb.shadow.gray.0}"
        },
        "hover": {
          "$type": "boxShadow",
          "$value": "{bb.shadow.gray.0}"
        },
        "active": {
          "$type": "boxShadow",
          "$value": "{bb.shadow.gray.0}"
        },
        "focus": {
          "$type": "boxShadow",
          "$value": "{bb.shadow.gray.0}"
        },
        "disabled": {
          "$type": "boxShadow",
          "$value": "{bb.shadow.gray.0}"
        }
      },
      "secondary": {
        "base": {
          "$type": "boxShadow",
          "$value": "{bb.shadow.gray.0}"
        },
        "hover": {
          "$type": "boxShadow",
          "$value": "{bb.shadow.gray.0}"
        },
        "active": {
          "$type": "boxShadow",
          "$value": "{bb.shadow.gray.0}"
        },
        "focus": {
          "$type": "boxShadow",
          "$value": "{bb.shadow.gray.0}"
        },
        "disabled": {
          "$type": "boxShadow",
          "$value": "{bb.shadow.gray.0}"
        }
      },
      "tertiary": {
        "base": {
          "$type": "boxShadow",
          "$value": "{bb.shadow.gray.0}"
        },
        "hover": {
          "$type": "boxShadow",
          "$value": "{bb.shadow.gray.0}"
        },
        "active": {
          "$type": "boxShadow",
          "$value": "{bb.shadow.gray.0}"
        },
        "focus": {
          "$type": "boxShadow",
          "$value": "{bb.shadow.gray.0}"
        },
        "disabled": {
          "$type": "boxShadow",
          "$value": "{bb.shadow.gray.0}"
        }
      },
      "danger": {
        "base": {
          "$type": "boxShadow",
          "$value": "{bb.shadow.gray.0}"
        },
        "hover": {
          "$type": "boxShadow",
          "$value": "{bb.shadow.gray.0}"
        },
        "active": {
          "$type": "boxShadow",
          "$value": "{bb.shadow.gray.0}"
        },
        "focus": {
          "$type": "boxShadow",
          "$value": "{bb.shadow.gray.0}"
        },
        "disabled": {
          "$type": "boxShadow",
          "$value": "{bb.shadow.gray.0}"
        }
      },
      "input": {
        "base": {
          "$type": "boxShadow",
          "$value": "{bb.shadow.gray.0}"
        },
        "hover": {
          "$type": "boxShadow",
          "$value": "{bb.shadow.gray.0}"
        },
        "active": {
          "$type": "boxShadow",
          "$value": "{bb.shadow.gray.0}"
        },
        "focus": {
          "$type": "boxShadow",
          "$value": "{bb.shadow.gray.0}"
        },
        "disabled": {
          "$type": "boxShadow",
          "$value": "{bb.shadow.gray.0}"
        }
      },
      "toolbar": {
        "base": {
          "$type": "boxShadow",
          "$value": "{bb.shadow.gray.0}"
        },
        "hover": {
          "$type": "boxShadow",
          "$value": "{bb.shadow.gray.0}"
        },
        "active": {
          "$type": "boxShadow",
          "$value": "{bb.shadow.gray.0}"
        },
        "focus": {
          "$type": "boxShadow",
          "$value": "{bb.shadow.gray.0}"
        },
        "disabled": {
          "$type": "boxShadow",
          "$value": "{bb.shadow.gray.0}"
        }
      }
    },
    "input": {
      "base": {
        "$type": "boxShadow",
        "$value": "{bb.shadow.gray.0}"
      },
      "disabled": {
        "$type": "boxShadow",
        "$value": "{bb.shadow.gray.0}"
      }
    }
  },
  "opacity": {
    "wait": {
      "$type": "opacity",
      "$value": "{bb.opacity.600}"
    }
  },
  "image": {
    "logo": {
      "primary": {
        "src": {
          "$type": "other",
          "$value": "{bb.image.logo.primary.src}"
        }
      }
    },
    "select_icon": {
      "base": {
        "$type": "other",
        "$value": "{bb.image.select_icon.base.light.src}"
      },
      "disabled": {
        "$type": "other",
        "$value": "{bb.image.select_icon.disabled.base.light.src}"
      }
    }
  },
  "brand": {
    "name": {
      "$type": "other",
      "$value": "{bb.brand.name}"
    }
  }
}