{
  "color": {
    "background": {
      "action": {
        "$type": "color",
        "$value": "{bb.color.blue.800}"
      },
      "container": {
        "$type": "color",
        "$value": "{bb.color.gray.900}"
      },
      "page": {
        "$type": "color",
        "$value": "{bb.color.gray.1100}"
      }
    },
    "text": {
      "default": {
        "$type": "color",
        "$value": "{bb.color.gray.25}"
      },
      "action": {
        "$type": "color",
        "$value": "{bb.color.blue.300}"
      },
      "deemphasized": {
        "$type": "color",
        "$value": "{bb.color.gray.200}"
      },
      "danger": {
        "$type": "color",
        "$value": "{bb.color.red.600}"
      },
      "inverse": {
        "$type": "color",
        "$value": "{bb.color.black}"
      },
      "heading": {
        "$type": "color",
        "$value": "{bb.color.green.600}"
      }
    },
    "icon": {
      "action": {
        "$type": "color",
        "$value": "{bb.color.blue.300}"
      },
      "inverse": {
        "$type": "color",
        "$value": "{bb.color.black}"
      }
    },
    "border": {
      "neutral_soft": {
        "$type": "color",
        "$value": "{bb.color.gray.600}"
      },
      "input": {
        "base": {
          "$type": "color",
          "$value": "{bb.color.gray.600}"
        },
        "hover": {
          "$type": "color",
          "$value": "{bb.color.blue.300}"
        },
        "active": {
          "$type": "color",
          "$value": "{bb.color.blue.300}"
        },
        "focus": {
          "$type": "color",
          "$value": "{bb.color.blue.300}"
        },
        "disabled": {
          "$type": "color",
          "$value": "{bb.color.gray.600}"
        },
        "error": {
          "$type": "color",
          "$value": "{bb.color.red.600}"
        }
      }
    }
  }
}