{
  "color": {
    "text": {
      "default": {
        "$type": "color",
        "$value": "{sky.abstract.color.primary_text}"
      },
      "deemphasized": {
        "$type": "color",
        "$value": "{sky.abstract.color.secondary_text}"
      },
      "action": {
        "$type": "color",
        "$value": "{sky.abstract.color.primary_interaction}"
      },
      "danger": {
        "$type": "color",
        "$value": "{bb.color.red.600}"
      },
      "inverse": {
        "$type": "color",
        "$value": "{bb.color.white}"
      },
      "heading": {
        "$type": "color",
        "$value": "{sky.abstract.color.heading_text}"
      },
      "link_highlighted": {
        "$type": "color",
        "$value": "{bb.color.blue.800}"
      }
    },
    "icon": {
      "default": {
        "$type": "color",
        "$value": "{sky.abstract.color.primary_text}"
      },
      "deemphasized": {
        "$type": "color",
        "$value": "{sky.abstract.color.secondary_text}"
      },
      "danger": {
        "$type": "color",
        "$value": "{bb.color.red.600}"
      },
      "warning": {
        "$type": "color",
        "$value": "{bb.color.yellow.600}"
      },
      "success": {
        "$type": "color",
        "$value": "{bb.color.green.600}"
      },
      "info": {
        "$type": "color",
        "$value": "{sky.abstract.color.primary_interaction}"
      },
      "inverse": {
        "$type": "color",
        "$value": "{bb.color.white}"
      },
      "action": {
        "$type": "color",
        "$value": "{sky.abstract.color.primary_interaction}"
      }
    },
    "background": {
      "page": {
        "$type": "color",
        "$value": "{bb.color.gray.25}"
      },
      "scrim": {
        "$type": "color",
        "$value": "{bb.color.scrim}"
      },
      "text_highlight": {
        "$type": "color",
        "$value": "{bb.color.yellow.400}"
      },
      "container": {
        "base": {
          "$type": "color",
          "$value": "{bb.color.white}"
        },
        "menu": {
          "$type": "color",
          "$value": "{bb.color.white}"
        },
        "danger": {
          "$type": "color",
          "$value": "{bb.color.red.300}"
        },
        "warning": {
          "$type": "color",
          "$value": "{bb.color.yellow.300}"
        },
        "success": {
          "$type": "color",
          "$value": "{bb.color.green.300}"
        },
        "info": {
          "$type": "color",
          "$value": "{bb.color.blue.100}"
        }
      },
      "action": {
        "primary": {
          "base": {
            "$type": "color",
            "$value": "{sky.abstract.color.primary_interaction}"
          },
          "hover": {
            "$type": "color",
            "$value": "{sky.abstract.color.primary_interaction}"
          },
          "active": {
            "$type": "color",
            "$value": "{sky.abstract.color.primary_interaction}"
          },
          "focus": {
            "$type": "color",
            "$value": "{sky.abstract.color.primary_interaction}"
          },
          "disabled": {
            "$type": "color",
            "$value": "{bb.color.gray.50}"
          }
        },
        "secondary": {
          "base": {
            "$type": "color",
            "$value": "{bb.color.white}"
          },
          "hover": {
            "$type": "color",
            "$value": "{bb.color.white}"
          },
          "active": {
            "$type": "color",
            "$value": "{bb.color.white}"
          },
          "focus": {
            "$type": "color",
            "$value": "{bb.color.white}"
          },
          "disabled": {
            "$type": "color",
            "$value": "{bb.color.gray.50}"
          }
        },
        "tertiary": {
          "base": {
            "$type": "color",
            "$value": "{bb.color.transparent}"
          },
          "hover": {
            "$type": "color",
            "$value": "{bb.color.transparent}"
          },
          "active": {
            "$type": "color",
            "$value": "{bb.color.transparent}"
          },
          "focus": {
            "$type": "color",
            "$value": "{bb.color.transparent}"
          },
          "disabled": {
            "$type": "color",
            "$value": "{bb.color.gray.50}"
          }
        },
        "danger": {
          "base": {
            "$type": "color",
            "$value": "{bb.color.red.600}"
          },
          "hover": {
            "$type": "color",
            "$value": "{bb.color.red.600}"
          },
          "active": {
            "$type": "color",
            "$value": "{bb.color.red.600}"
          },
          "focus": {
            "$type": "color",
            "$value": "{bb.color.red.600}"
          },
          "disabled": {
            "$type": "color",
            "$value": "{bb.color.gray.50}"
          }
        },
        "input": {
          "base": {
            "$type": "color",
            "$value": "{bb.color.transparent}"
          },
          "hover": {
            "$type": "color",
            "$value": "{bb.color.transparent}"
          },
          "active": {
            "$type": "color",
            "$value": "{bb.color.transparent}"
          },
          "focus": {
            "$type": "color",
            "$value": "{bb.color.transparent}"
          },
          "disabled": {
            "$type": "color",
            "$value": "{bb.color.gray.50}"
          }
        }
      },
      "input": {
        "base": {
          "$type": "color",
          "$value": "{bb.color.transparent}"
        },
        "disabled": {
          "$type": "color",
          "$value": "{bb.color.gray.50}"
        }
      },
      "thumb": {
        "base": {
          "$type": "color",
          "$value": "{bb.color.white}"
        },
        "disabled": {
          "$type": "color",
          "$value": "{bb.color.gray.50}"
        }
      },
      "selected": {
        "heavy": {
          "$type": "color",
          "$value": "{sky.abstract.color.primary_interaction}"
        },
        "soft": {
          "$type": "color",
          "$value": "{bb.color.blue.100}"
        },
        "danger": {
          "$type": "color",
          "$value": "{bb.color.red.300}"
        },
        "warning": {
          "$type": "color",
          "$value": "{bb.color.yellow.300}"
        },
        "success": {
          "$type": "color",
          "$value": "{bb.color.green.300}"
        }
      },
      "nav": {
        "base": {
          "$type": "color",
          "$value": "{bb.color.transparent}"
        },
        "hover": {
          "$type": "color",
          "$value": "{bb.color.transparent}"
        },
        "active": {
          "$type": "color",
          "$value": "{bb.color.transparent}"
        },
        "focus": {
          "$type": "color",
          "$value": "{bb.color.transparent}"
        },
        "disabled": {
          "$type": "color",
          "$value": "{bb.color.gray.50}"
        }
      },
      "list": {
        "base": {
          "$type": "color",
          "$value": "{bb.color.transparent}"
        },
        "hover": {
          "$type": "color",
          "$value": "{bb.color.transparent}"
        },
        "active": {
          "$type": "color",
          "$value": "{bb.color.transparent}"
        },
        "focus": {
          "$type": "color",
          "$value": "{bb.color.transparent}"
        },
        "disabled": {
          "$type": "color",
          "$value": "{bb.color.gray.50}"
        }
      },
      "file_drop": {
        "$type": "color",
        "$value": "{bb.color.gray.25}"
      },
      "thumbnail_matte": {
        "$type": "color",
        "$value": "{bb.color.white}"
      },
      "icon_matte": {
        "$type": "color",
        "$value": "{bb.color.blue.100}"
      }
    },
    "border": {
      "selected": {
        "$type": "color",
        "$value": "{sky.abstract.color.primary_interaction}"
      },
      "selected_soft": {
        "$type": "color",
        "$value": "{bb.color.blue.300}"
      },
      "danger": {
        "$type": "color",
        "$value": "{bb.color.red.600}"
      },
      "warning": {
        "$type": "color",
        "$value": "{bb.color.yellow.600}"
      },
      "success": {
        "$type": "color",
        "$value": "{bb.color.green.600}"
      },
      "info": {
        "$type": "color",
        "$value": "{sky.abstract.color.primary_interaction}"
      },
      "divider": {
        "$type": "color",
        "$value": "{sky.abstract.color.light_border}"
      },
      "elevation": {
        "$type": "color",
        "$value": "{sky.abstract.color.light_border}"
      },
      "text_highlight": {
        "$type": "color",
        "$value": "{bb.color.yellow.800}"
      },
      "action": {
        "primary": {
          "base": {
            "$type": "color",
            "$value": "{sky.abstract.color.primary_interaction}"
          },
          "hover": {
            "$type": "color",
            "$value": "{bb.color.blue.200}"
          },
          "active": {
            "$type": "color",
            "$value": "{bb.color.blue.200}"
          },
          "focus": {
            "$type": "color",
            "$value": "{bb.color.blue.200}"
          },
          "disabled": {
            "$type": "color",
            "$value": "{sky.abstract.color.light_border}"
          }
        },
        "secondary": {
          "base": {
            "$type": "color",
            "$value": "{sky.abstract.color.light_border}"
          },
          "hover": {
            "$type": "color",
            "$value": "{sky.abstract.color.primary_interaction}"
          },
          "active": {
            "$type": "color",
            "$value": "{sky.abstract.color.primary_interaction}"
          },
          "focus": {
            "$type": "color",
            "$value": "{sky.abstract.color.primary_interaction}"
          },
          "disabled": {
            "$type": "color",
            "$value": "{sky.abstract.color.light_border}"
          }
        },
        "tertiary": {
          "base": {
            "$type": "color",
            "$value": "{bb.color.transparent}"
          },
          "hover": {
            "$type": "color",
            "$value": "{sky.abstract.color.primary_interaction}"
          },
          "active": {
            "$type": "color",
            "$value": "{sky.abstract.color.primary_interaction}"
          },
          "focus": {
            "$type": "color",
            "$value": "{sky.abstract.color.primary_interaction}"
          },
          "disabled": {
            "$type": "color",
            "$value": "{sky.abstract.color.light_border}"
          }
        },
        "danger": {
          "base": {
            "$type": "color",
            "$value": "{bb.color.red.600}"
          },
          "hover": {
            "$type": "color",
            "$value": "{bb.color.red.200}"
          },
          "active": {
            "$type": "color",
            "$value": "{bb.color.red.200}"
          },
          "focus": {
            "$type": "color",
            "$value": "{bb.color.red.200}"
          },
          "disabled": {
            "$type": "color",
            "$value": "{sky.abstract.color.light_border}"
          }
        },
        "input": {
          "base": {
            "$type": "color",
            "$value": "{sky.abstract.color.dark_border}"
          },
          "hover": {
            "$type": "color",
            "$value": "{sky.abstract.color.primary_interaction}"
          },
          "active": {
            "$type": "color",
            "$value": "{sky.abstract.color.primary_interaction}"
          },
          "focus": {
            "$type": "color",
            "$value": "{sky.abstract.color.primary_interaction}"
          },
          "disabled": {
            "$type": "color",
            "$value": "{sky.abstract.color.dark_border}"
          }
        }
      },
      "container": {
        "base": {
          "$type": "color",
          "$value": "{sky.abstract.color.light_border}"
        }
      },
      "input": {
        "base": {
          "$type": "color",
          "$value": "{sky.abstract.color.dark_border}"
        },
        "hover": {
          "$type": "color",
          "$value": "{sky.abstract.color.primary_interaction}"
        },
        "active": {
          "$type": "color",
          "$value": "{sky.abstract.color.primary_interaction}"
        },
        "focus": {
          "$type": "color",
          "$value": "{sky.abstract.color.primary_interaction}"
        },
        "disabled": {
          "$type": "color",
          "$value": "{sky.abstract.color.dark_border}"
        },
        "error": {
          "$type": "color",
          "$value": "{bb.color.red.600}"
        }
      },
      "separator": {
        "dark": {
          "$type": "color",
          "$value": "{sky.abstract.color.dark_border}"
        },
        "light": {
          "$type": "color",
          "$value": "{sky.abstract.color.light_border}"
        },
        "row": {
          "$type": "color",
          "$value": "{sky.abstract.color.light_border}"
        }
      }
    }
  },
  "elevation": {
    "none": {
      "$type": "boxShadow",
      "$value": "{bb.shadow.gray.0}"
    },
    "focus": {
      "$type": "boxShadow",
      "$value": "{bb.shadow.gray.2}"
    },
    "overflow": {
      "$type": "boxShadow",
      "$value": "{bb.shadow.gray.2}"
    },
    "raised": {
      "100": {
        "$type": "boxShadow",
        "$value": "{bb.shadow.gray.1}"
      }
    },
    "overlay": {
      "100": {
        "$type": "boxShadow",
        "$value": "{bb.shadow.gray.4}"
      },
      "200": {
        "$type": "boxShadow",
        "$value": "{bb.shadow.gray.8}"
      },
      "300": {
        "$type": "boxShadow",
        "$value": "{bb.shadow.gray.16}"
      },
      "400": {
        "$type": "boxShadow",
        "$value": "{bb.shadow.gray.24}"
      }
    }
  }
}