{
    "background-color": {
      "$type": "color",
      "danger": {
        "$value": "#f7a08f"
      },
      "disabled": {
        "$value": "#191e23"
      },
      "elevation-0": {
        "$value": "#ef4044"
      },
      "elevation-1": {
        "$value": "#1e2229"
      },
      "elevation-3": {
        "$value": "#242b2e"
      },
      "elevation-4": {
        "$value": "#292d34"
      },
      "elevation-8": {
        "$value": "#2f3339"
      },
      "elevation-16": {
        "$value": "#1e2229"
      },
      "elevation-24": {
        "$value": "#27292c"
      },
      "info": {
        "$value": "#86b3f3"
      },
      "input-selected": {
        "$value": "123e4c"
      },
      "neutral-light": {
        "$value": "#161a1f"
      },
      "primary-dark": {
        "$value": "#00cfff"
      },
      "page-default": {
        "$value": "#161a1f"
      },
      "success": {
        "$value": "#b7da9b"
      },
      "warning": {
        "$value": "#ffd597"
      }
    },
    "border-color": {
      "$type": "color",
      "neutral-medium": {
        "$value": "#919498"
      }
    },
    "highlight-color": {
      "$type": "color",
      "info": {
        "$value": "#5091ed"
      }
    }
  }

